darkswarm/__init__.py
darkswarm/manager.py
darkswarm-0.2.2.dist-info/WHEEL
darkswarm-0.2.2.dist-info/METADATA
darkswarm-0.2.2.dist-info/RECORD
