Metadata-Version: 2.1
Name: darkswarm
Version: 0.2.2
Summary: Darkswarm is manual preload service/containers for docker swarm
Home-page: https://github.com/Kjwon15/darkswarm/
Keywords: docker,swarm
Author: Jeong Arm
Author-email: arm@gurum.cc
Requires-Python: >=3.7,<4.0
Classifier: Programming Language :: Python :: 3
Classifier: Programming Language :: Python :: 3.7
Classifier: Programming Language :: Python :: 3.8
Classifier: Programming Language :: Python :: 3.9
Requires-Dist: docker[ssh] (>=4.3.1,<5.0.0)
Project-URL: Repository, https://github.com/Kjwon15/darkswarm/
